scadable/__init__.py
scadable/connection.py
scadable/device.py
scadable/facility.py
scadable-1.0.0.dist-info/licenses/LICENSE
scadable-1.0.0.dist-info/METADATA
scadable-1.0.0.dist-info/WHEEL
scadable-1.0.0.dist-info/top_level.txt
scadable-1.0.0.dist-info/RECORD
