Metadata-Version: 2.4
Name: scadable
Version: 1.0.0
Summary: A Python library for scalable and modular software development.
Author: Christopher Li
License-Expression: Apache-2.0
Project-URL: Homepage, https://github.com/scadable/library-python
Project-URL: Bug Tracker, https://github.com/scadable/library-python/issues
Classifier: Programming Language :: Python
Classifier: Programming Language :: Python :: 3
Classifier: Programming Language :: Python :: 3 :: Only
Classifier: Programming Language :: Python :: 3.10
Classifier: Programming Language :: Python :: 3.11
Classifier: Programming Language :: Python :: 3.12
Classifier: Programming Language :: Python :: 3.13
Classifier: Operating System :: OS Independent
Requires-Python: >=3.10
License-File: LICENSE
Requires-Dist: websockets>=13.0
Provides-Extra: dev
Requires-Dist: pytest; extra == "dev"
Requires-Dist: coverage; extra == "dev"
Requires-Dist: pytest-cov; extra == "dev"
Requires-Dist: pytest-asyncio; extra == "dev"
Requires-Dist: pre-commit; extra == "dev"
Dynamic: license-file
